{
  "$schema": "../../../schema/formal_claim_v1.2.schema.json",
  "schema_version": "v1.2",
  "id": "sha256-PLACEHOLDER_COMPUTE_AT_CANONICALIZATION",
  "exp_number": 15,
  "title": "Methylation cell-type variance at TE boundaries is class-specific — LTR/LINE/DNA elements show ~0.019 cross-cell-type variance, SINE only 0.014, with TE-free regions at 0.018 as baseline",
  "posted_at": "2026-04-19",
  "api_version": "0.9.x",
  "data_version": "polymer-db@2026-04-08",
  "version": "1.0.0",
  "domain": "genomic",
  "subject": {
    "kind": "cohort",
    "id": "polymer:cohorts/migration/te_methylation_class_specific_at_boundary",
    "display": "Migration cohort for 'Methylation cell-type variance at TE boundaries is class-specific — LTR/LINE/DNA'",
    "definition": {
      "source_dataset": {
        "name": "Polymer TE surveillance corpus",
        "version": "repeatmasker_hg38_v1",
        "extra": {
          "first_premise_layer": "te_class_assignments"
        }
      },
      "inclusion": [],
      "exclusion": [],
      "cardinality": null,
      "random_seed": null
    },
    "members_hash": "migration:v1_1_to_v1_2/te_methylation_class_specific_at_boundary",
    "note": "Inclusion predicates intentionally empty at migration time; the implicit member set is defined by the v1.1 premises. Re-author with explicit inclusion predicates to tighten the subject."
  },
  "context": {
    "assembly": "GRCh38.p14"
  },
  "premises": [
    {
      "id": "p_te_classified_autosomal",
      "source": {
        "layer": "te_class_assignments",
        "version": "repeatmasker_hg38_v1",
        "provenance_state": "fly_postgres",
        "note": "Per-TE class assignment from RepeatMasker; autosomal TEs only."
      },
      "predicate": {
        "kind": "and",
        "terms": [
          {
            "kind": "cmp",
            "col": "te_class",
            "op": "in",
            "rhs": [
              "LINE",
              "SINE",
              "LTR",
              "DNA"
            ]
          },
          {
            "kind": "cmp",
            "col": "chromosome_class",
            "op": "=",
            "rhs": "autosomal"
          }
        ]
      },
      "cardinality": null,
      "content_hash": "blake3-PLACEHOLDER_COMPUTE_ON_EVALUATE"
    },
    {
      "id": "p_wgbs_methylation_6_celltypes",
      "source": {
        "layer": "blueprint_wgbs_methylation_6_celltypes",
        "version": "blueprint_wgbs_v1",
        "provenance_state": "local_rds",
        "note": "BLUEPRINT/Roadmap WGBS methylation profiles for 6 hematopoietic cell types (monocyte, neutrophil, B_naive, T_naive, HSC, NK) at 500-bp bins flanking TE boundaries. Variance taken across the 6 cell types per bin."
      },
      "predicate": {
        "kind": "cmp",
        "col": "celltype",
        "op": "in",
        "rhs": [
          "monocyte",
          "neutrophil",
          "b_naive",
          "t_naive",
          "hsc",
          "nk"
        ]
      },
      "cardinality": 6,
      "content_hash": "blake3-PLACEHOLDER_COMPUTE_ON_EVALUATE"
    }
  ],
  "operations": [
    {
      "id": "o_boundary_bins_per_te",
      "kind": "filter",
      "inputs": [
        "p_te_classified_autosomal"
      ],
      "predicate": {
        "kind": "cmp",
        "col": "offset_bp_from_boundary",
        "op": "in",
        "rhs": [
          -5000,
          -4500,
          -4000,
          -3500,
          -3000,
          -2500,
          -2000,
          -1500,
          -1000,
          -500,
          0,
          500,
          1000,
          1500,
          2000,
          2500,
          3000,
          3500,
          4000,
          4500,
          5000
        ]
      },
      "note": "21 500-bp offset bins across ±5 kb from each TE boundary (5' and 3')."
    },
    {
      "id": "o_per_bin_celltype_variance",
      "kind": "estimator",
      "inputs": [
        "o_boundary_bins_per_te",
        "p_wgbs_methylation_6_celltypes"
      ],
      "estimator": {
        "name": "per_bin_variance_across_celltypes",
        "impl": "python::polymer_genomics.stats.variance_across_groups",
        "version": "polymer_genomics@0.3.x",
        "features": {
          "label": "celltype_methylation",
          "select": [
            "mean_monocyte",
            "mean_neutrophil",
            "mean_b_naive",
            "mean_t_naive",
            "mean_hsc",
            "mean_nk"
          ]
        },
        "params": {
          "var_function": "sample_variance",
          "ddof": 1
        }
      },
      "note": "Per-bin across-celltype methylation variance. 246,102 bins at LTR, 586,948 LINE, 58,493 DNA, 366,269 SINE, 218,087 TE-free (values in methylation_celltype_variance.csv)."
    },
    {
      "id": "o_aggregate_mean_variance_per_class",
      "kind": "aggregate",
      "inputs": [
        "o_per_bin_celltype_variance"
      ],
      "by": [
        "te_class"
      ],
      "agg": [
        {
          "col": "per_bin_variance",
          "fn": "mean",
          "na_rm": true
        }
      ],
      "note": "Per-class mean of the per-bin cross-celltype variance."
    }
  ],
  "statistics": [
    {
      "id": "s_per_class_mean_variance",
      "produced_by": "o_aggregate_mean_variance_per_class",
      "name": "mean_cross_celltype_methylation_variance_by_te_class",
      "value": [
        {
          "label": "LTR",
          "value": 0.01995
        },
        {
          "label": "LINE",
          "value": 0.01939
        },
        {
          "label": "DNA",
          "value": 0.01907
        },
        {
          "label": "TE_free_baseline",
          "value": 0.01776
        },
        {
          "label": "SINE",
          "value": 0.01403
        }
      ],
      "n": 1475899,
      "evidence_class": "S",
      "note": "Mean per-bin variance across the 6 hematopoietic cell types, per TE class. Values from methylation_celltype_variance.csv. LTR highest (young, actively regulated), SINE lowest (ancient, constitutively methylated)."
    },
    {
      "id": "s_ltr_variance",
      "produced_by": "o_aggregate_mean_variance_per_class",
      "name": "ltr_mean_cross_celltype_variance",
      "value": 0.01995,
      "evidence_class": "S"
    },
    {
      "id": "s_sine_variance",
      "produced_by": "o_aggregate_mean_variance_per_class",
      "name": "sine_mean_cross_celltype_variance",
      "value": 0.01403,
      "evidence_class": "S"
    },
    {
      "id": "s_te_free_variance_baseline",
      "produced_by": "o_aggregate_mean_variance_per_class",
      "name": "te_free_mean_cross_celltype_variance",
      "value": 0.01776,
      "evidence_class": "S",
      "note": "TE-free baseline: a control bin population not flanking any TE. LTR > baseline > SINE."
    },
    {
      "id": "s_per_class_mean_beta",
      "produced_by": "o_aggregate_mean_variance_per_class",
      "name": "mean_beta_overall_by_te_class",
      "value": [
        {
          "label": "SINE_mean_beta",
          "value": 0.7812
        },
        {
          "label": "DNA_mean_beta",
          "value": 0.7437
        },
        {
          "label": "LINE_mean_beta",
          "value": 0.7375
        },
        {
          "label": "LTR_mean_beta",
          "value": 0.7236
        },
        {
          "label": "TE_free_mean_beta",
          "value": 0.7051
        }
      ],
      "n": 1475899,
      "evidence_class": "S",
      "note": "Mean methylation β per TE class. SINE is most methylated (0.78 — consistent with constitutive heavy methylation), TE-free least (0.71). The β and variance orderings are almost inverted: high β / low variance = constitutive, low β / high variance = regulated."
    }
  ],
  "inference": {
    "expression": {
      "kind": "and",
      "terms": [
        {
          "kind": "cmp",
          "lhs": {
            "stat_id": "s_ltr_variance"
          },
          "op": ">",
          "rhs": {
            "stat_id": "s_sine_variance"
          }
        },
        {
          "kind": "cmp",
          "lhs": {
            "stat_id": "s_ltr_variance"
          },
          "op": ">",
          "rhs": {
            "stat_id": "s_te_free_variance_baseline"
          }
        },
        {
          "kind": "cmp",
          "lhs": {
            "stat_id": "s_sine_variance"
          },
          "op": "<",
          "rhs": {
            "stat_id": "s_te_free_variance_baseline"
          }
        },
        {
          "kind": "cmp",
          "lhs": {
            "stat_id": "s_ltr_variance"
          },
          "op": ">",
          "rhs": 0.015
        }
      ]
    },
    "justification": "Four conjuncts license the class-specific regulation claim: (1) LTR variance > SINE variance — stat-vs-stat — the core dichotomy (young LTR regulated, ancient SINE constitutive); (2) LTR > TE-free baseline — stat-vs-stat — LTR regulation is real, not just inherited from genomic position; (3) SINE < TE-free baseline — stat-vs-stat — SINE is specifically constitutive, below background, the asymmetric complement to LTR; (4) absolute LTR variance > 0.015 ensures the signal is substantive rather than a marginal ranking. The three stat-vs-stat comparisons together establish LTR > baseline > SINE, the full class-specificity claim.",
    "failure_mode": "If LTR variance fell to baseline, the 'young LTRs are the actively regulated fraction' framing collapses. If SINE variance rose above baseline, the constitutive-methylation claim for ancient elements fails. If the LTR > SINE direction reversed, the age-inverted regulation pattern would dissolve."
  },
  "conclusion": {
    "assertion": "Methylation cell-type variance at TE boundaries is class-specific: LTR elements show the highest cross-cell-type variance (0.0199 across 6 hematopoietic cell types), followed by LINE (0.0194) and DNA (0.0191); TE-free regions sit at 0.0178; SINE elements are lowest at 0.0140. The LTR > TE-free > SINE ordering — combined with inverse β-value rank (SINE highest mean β = 0.78, LTR lowest = 0.72) — supports the model that young LTR/ERV elements are the actively regulated fraction, while ancient SINEs are constitutively heavily methylated.",
    "formal": null,
    "scope": {
      "layers": [
        {
          "layer": "te_class_assignments",
          "version": "repeatmasker_hg38_v1",
          "provenance_state": "fly_postgres"
        },
        {
          "layer": "blueprint_wgbs_methylation_6_celltypes",
          "version": "blueprint_wgbs_v1",
          "provenance_state": "local_rds"
        }
      ],
      "restrictions": {
        "kind": "and",
        "terms": [
          {
            "kind": "cmp",
            "col": "te_class",
            "op": "in",
            "rhs": [
              "LINE",
              "SINE",
              "LTR",
              "DNA"
            ]
          },
          {
            "kind": "cmp",
            "col": "offset_bp_abs_from_boundary",
            "op": "<=",
            "rhs": 5000
          },
          {
            "kind": "cmp",
            "col": "bin_width_bp",
            "op": "=",
            "rhs": 500
          }
        ]
      },
      "scale_note": "Boundary-flank scope (±5 kb). TE-interior methylation is a related but separate claim. Reference-only methylation (germline) — PCAWG somatic methylation dynamics are deferred per PAPER_OUTLINE § limitations."
    },
    "confidence": {
      "type": "frequentist",
      "value": null,
      "note": "Variance computed over n >= 58k bins per class; formal inferential test (e.g. per-class permutation null) staged but not pinned."
    },
    "outcome": "positive"
  },
  "depends_on": [],
  "external_assumptions": [
    {
      "statement": "6 BLUEPRINT hematopoietic cell types are sufficient to estimate cross-cell-type methylation variance at TE boundaries; additional tissues would increase variance estimates but preserve relative ordering.",
      "kind": "design_choice",
      "citation": "paper_te_expression_atlas § Methods",
      "confidence": 0.75
    },
    {
      "statement": "1 kb effective resolution (500-bp bins) is an accepted lower bound for WGBS-based boundary analysis; finer resolution requires targeted bisulfite sequencing and is deferred.",
      "kind": "design_choice",
      "citation": "PAPER_OUTLINE § limitations",
      "confidence": 0.85
    },
    {
      "statement": "TE-free regions with matched distance-to-TSS and GC distribution are a valid baseline; a more aggressive control (matched by gene-regulatory context) would further narrow the interpretation but would not change the LTR > baseline > SINE ordering.",
      "kind": "design_choice",
      "citation": null,
      "confidence": 0.7
    }
  ],
  "notebook": "internal/InSilico/TE surveillance/provenance/exp15_te_gene_correlation/R/04_methylation_boundary_metagene.R"
}
