{
  "$schema": "../../../schema/formal_claim_v1.2.schema.json",
  "schema_version": "v1.2",
  "id": "sha256-PLACEHOLDER_COMPUTE_AT_CANONICALIZATION",
  "exp_number": 3,
  "title": "Multi-tissue overall: biophysics adds mean delta AUROC = +0.082 to TE silencing prediction across 5 representative tissues",
  "posted_at": "2026-03-23",
  "api_version": "0.9.x",
  "data_version": "polymer-db@2026-03-23",
  "version": "1.0.0",
  "domain": "genomic",
  "subject": {
    "kind": "cohort",
    "id": "polymer:cohorts/migration/te_silencing_biophysics_overall_auroc",
    "display": "Migration cohort for 'Multi-tissue overall: biophysics adds mean delta AUROC = +0.082 to TE silencing '",
    "definition": {
      "source_dataset": {
        "name": "Polymer TE surveillance corpus",
        "version": "repeatmasker_hg38_v4.0.5",
        "extra": {
          "first_premise_layer": "repeats_repeatmasker"
        }
      },
      "inclusion": [],
      "exclusion": [],
      "cardinality": null,
      "random_seed": null
    },
    "members_hash": "migration:v1_1_to_v1_2/te_silencing_biophysics_overall_auroc",
    "note": "Inclusion predicates intentionally empty at migration time; the implicit member set is defined by the v1.1 premises. Re-author with explicit inclusion predicates to tighten the subject."
  },
  "context": {
    "assembly": "GRCh38.p14"
  },
  "premises": [
    {
      "id": "p_te_full",
      "source": {
        "layer": "repeats_repeatmasker",
        "version": "repeatmasker_hg38_v4.0.5",
        "provenance_state": "fly_postgres"
      },
      "predicate": {
        "kind": "and",
        "terms": [
          {
            "kind": "cmp",
            "col": "chr",
            "op": "in",
            "rhs": [
              "chr1",
              "chr2",
              "chr3",
              "chr4",
              "chr5",
              "chr6",
              "chr7",
              "chr8",
              "chr9",
              "chr10",
              "chr11",
              "chr12",
              "chr13",
              "chr14",
              "chr15",
              "chr16",
              "chr17",
              "chr18",
              "chr19",
              "chr20",
              "chr21",
              "chr22"
            ]
          },
          {
            "kind": "cmp",
            "col": "te_class",
            "op": "in",
            "rhs": [
              "LINE",
              "SINE",
              "LTR",
              "DNA"
            ]
          }
        ]
      },
      "cardinality": 5006091,
      "content_hash": "blake3-PLACEHOLDER_COMPUTE_ON_EVALUATE"
    },
    {
      "id": "p_chromhmm_5tissues",
      "source": {
        "layer": "chromhmm_15state_roadmap",
        "version": "pehrsson_2019",
        "provenance_state": "local_rds",
        "note": "5 representative tissues selected for Phase 1 multi-tissue test."
      },
      "predicate": {
        "kind": "cmp",
        "col": "epigenome_id",
        "op": "in",
        "rhs": [
          "E003",
          "E029",
          "E062",
          "E066",
          "E123"
        ]
      },
      "cardinality": 5,
      "content_hash": "blake3-PLACEHOLDER_COMPUTE_ON_EVALUATE",
      "note": "E003 H1 ESC, E029 CD14 monocytes, E062 fetal brain, E066 liver, E123 K562 (CML)."
    },
    {
      "id": "p_biophysics_15tracks_1kb",
      "source": {
        "layer": "tracks_biophysics_1kb",
        "version": "polymer_evolution_phase1-3.5",
        "provenance_state": "local_rds"
      },
      "predicate": {
        "kind": "cmp",
        "col": "track",
        "op": "in",
        "rhs": [
          "stacking_dg37",
          "deformability",
          "curvature",
          "persistence_length",
          "delta_lp",
          "cpg_obs_exp",
          "methylation_sensitivity",
          "wrapping_energy",
          "predicted_occupancy",
          "ndr_score",
          "correlation_length",
          "integrated_response",
          "periodicity_power",
          "melting_temp",
          "groove_width"
        ]
      },
      "cardinality": null,
      "content_hash": "blake3-PLACEHOLDER_COMPUTE_ON_EVALUATE"
    }
  ],
  "operations": [
    {
      "id": "o_join_te_chromatin",
      "kind": "join",
      "inputs": [
        "p_te_full",
        "p_chromhmm_5tissues"
      ],
      "on": "te_id_x_chromhmm_overlap_majority"
    },
    {
      "id": "o_join_biophys",
      "kind": "join",
      "inputs": [
        "o_join_te_chromatin",
        "p_biophysics_15tracks_1kb"
      ],
      "on": "chr_window_1kb_overlap"
    },
    {
      "id": "o_cv_split",
      "kind": "cv_split",
      "inputs": [
        "o_join_biophys"
      ],
      "scheme": {
        "kind": "k_fold_by_chromosome",
        "k": 5,
        "seed": 42
      }
    },
    {
      "id": "o_rf_m0_per_tissue",
      "kind": "estimator",
      "inputs": [
        "o_join_biophys",
        "o_cv_split"
      ],
      "estimator": {
        "name": "rf_auroc_multiclass_per_tissue_baseline",
        "impl": "R::randomForest::randomForest",
        "version": "randomForest@4.7.x",
        "response": "chromatin_state_5class",
        "features": {
          "label": "m0_age_length_class",
          "select": [
            "divergence_pct",
            "te_length",
            "te_class"
          ]
        },
        "params": {
          "ntree": 500,
          "mtry": 2,
          "nodesize": 50,
          "sampsize": 50000,
          "seed": 42,
          "stratify_by": "epigenome_id"
        }
      }
    },
    {
      "id": "o_rf_m1_per_tissue",
      "kind": "estimator",
      "inputs": [
        "o_join_biophys",
        "o_cv_split"
      ],
      "estimator": {
        "name": "rf_auroc_multiclass_per_tissue_biophys",
        "impl": "R::randomForest::randomForest",
        "version": "randomForest@4.7.x",
        "response": "chromatin_state_5class",
        "features": {
          "label": "m1_baseline_plus_biophysics",
          "parent": "m0_age_length_class",
          "select": [
            "divergence_pct",
            "te_length",
            "te_class",
            "stacking_dg37",
            "deformability",
            "curvature",
            "persistence_length",
            "delta_lp",
            "cpg_obs_exp",
            "methylation_sensitivity",
            "wrapping_energy",
            "predicted_occupancy",
            "ndr_score",
            "correlation_length",
            "integrated_response",
            "periodicity_power",
            "melting_temp",
            "groove_width"
          ]
        },
        "params": {
          "ntree": 500,
          "mtry": 4,
          "nodesize": 50,
          "sampsize": 50000,
          "seed": 42,
          "stratify_by": "epigenome_id"
        }
      }
    }
  ],
  "statistics": [
    {
      "id": "s_per_tissue_m0_auroc",
      "produced_by": "o_rf_m0_per_tissue",
      "name": "auroc_per_tissue_m0",
      "value": [
        {
          "label": "E003_H1_ESC",
          "value": 0.632
        },
        {
          "label": "E029_CD14_monocyte",
          "value": 0.625
        },
        {
          "label": "E062_fetal_brain",
          "value": 0.649
        },
        {
          "label": "E066_liver",
          "value": 0.641
        },
        {
          "label": "E123_K562_CML",
          "value": 0.597
        }
      ],
      "evidence_class": "S"
    },
    {
      "id": "s_per_tissue_m1_auroc",
      "produced_by": "o_rf_m1_per_tissue",
      "name": "auroc_per_tissue_m1",
      "value": [
        {
          "label": "E003_H1_ESC",
          "value": 0.728
        },
        {
          "label": "E029_CD14_monocyte",
          "value": 0.71
        },
        {
          "label": "E062_fetal_brain",
          "value": 0.728
        },
        {
          "label": "E066_liver",
          "value": 0.684
        },
        {
          "label": "E123_K562_CML",
          "value": 0.705
        }
      ],
      "evidence_class": "S"
    },
    {
      "id": "s_per_tissue_delta",
      "produced_by": "o_rf_m1_per_tissue",
      "name": "delta_auroc_per_tissue_m1_minus_m0",
      "value": [
        {
          "label": "E003_H1_ESC",
          "value": 0.096
        },
        {
          "label": "E029_CD14_monocyte",
          "value": 0.085
        },
        {
          "label": "E062_fetal_brain",
          "value": 0.079
        },
        {
          "label": "E066_liver",
          "value": 0.043
        },
        {
          "label": "E123_K562_CML",
          "value": 0.109
        }
      ],
      "evidence_class": "D"
    },
    {
      "id": "s_mean_delta_across_tissues",
      "produced_by": "o_rf_m1_per_tissue",
      "name": "mean_delta_auroc_across_5_tissues",
      "value": 0.082,
      "evidence_class": "D",
      "note": "Mean of the per-tissue delta vector. Pre-registered STRONG threshold was +0.02; observed +0.082 -> 4x the threshold."
    },
    {
      "id": "s_min_delta",
      "produced_by": "o_rf_m1_per_tissue",
      "name": "min_delta_auroc_across_5_tissues",
      "value": 0.043,
      "evidence_class": "D",
      "note": "Worst-case tissue (E066 liver) still exceeds threshold by 2x. Robustness to tissue choice."
    }
  ],
  "inference": {
    "expression": {
      "kind": "and",
      "terms": [
        {
          "kind": "cmp",
          "lhs": {
            "stat_id": "s_mean_delta_across_tissues"
          },
          "op": ">",
          "rhs": 0.02
        },
        {
          "kind": "cmp",
          "lhs": {
            "stat_id": "s_min_delta"
          },
          "op": ">",
          "rhs": 0.02
        }
      ]
    },
    "justification": "Two conjuncts: (1) mean delta exceeds the pre-registered STRONG threshold +0.02; (2) every per-tissue delta exceeds it (tested via min-delta). The second conjunct rules out 'one tissue carries the average' — every tissue independently passes.",
    "failure_mode": "If s_min_delta < 0.02, the multi-tissue robustness claim collapses to a single-tissue claim. If s_mean_delta < 0.02, the entire result collapses."
  },
  "conclusion": {
    "assertion": "Across 5 representative Roadmap epigenomes (H1 ESC, CD14 monocytes, fetal brain, liver, K562 CML), DNA biophysical features improve TE silencing-mechanism prediction by mean delta AUROC = +0.082 (range +0.043 to +0.109), with every tissue exceeding the pre-registered +0.02 STRONG threshold. The biophysics-predicts-silencing claim is robust to cell type.",
    "formal": null,
    "scope": {
      "layers": [
        {
          "layer": "repeats_repeatmasker",
          "version": "repeatmasker_hg38_v4.0.5",
          "provenance_state": "fly_postgres"
        },
        {
          "layer": "chromhmm_15state_roadmap",
          "version": "pehrsson_2019",
          "provenance_state": "local_rds"
        },
        {
          "layer": "tracks_biophysics_1kb",
          "version": "polymer_evolution_phase1-3.5",
          "provenance_state": "local_rds"
        }
      ],
      "restrictions": {
        "kind": "cmp",
        "col": "epigenome_id",
        "op": "in",
        "rhs": [
          "E003",
          "E029",
          "E062",
          "E066",
          "E123"
        ]
      },
      "scale_note": "Multi-tissue parent claim. Within-age-class child (te_silencing_within_age_bivalent) tests the harder version on age-matched TEs; H3K9me3 negative control (te_silencing_h3k9me3_negative_control) tests the per-state specificity."
    },
    "confidence": {
      "type": "frequentist",
      "value": null
    },
    "outcome": "strong_positive"
  },
  "depends_on": [],
  "external_assumptions": [
    {
      "statement": "5 tissues selected for Phase 1 multi-tissue test are representative of the 127-epigenome Roadmap range; full sweep is deferred but is unlikely to materially change the mean delta.",
      "kind": "design_choice",
      "citation": null,
      "confidence": 0.8
    }
  ],
  "notebook": "internal/InSilico/TE surveillance/provenance/exp03_silencing_prediction/R/02_predict_silencing.R"
}
